comicfuryscraper/cli.py
comicfuryscraper/index.py
comicfuryscraper-1.0.1.dist-info/licenses/LICENSE
comicfuryscraper-1.0.1.dist-info/METADATA
comicfuryscraper-1.0.1.dist-info/WHEEL
comicfuryscraper-1.0.1.dist-info/entry_points.txt
comicfuryscraper-1.0.1.dist-info/top_level.txt
comicfuryscraper-1.0.1.dist-info/RECORD
