Metadata-Version: 2.4
Name: comicfuryscraper
Version: 1.0.1
Summary: A simple terminal CLI app to download ComicFury comics
Author-email: enzomtpYT <contact@enzomtp.party>
License-Expression: MIT
Requires-Python: >=3.9
License-File: LICENSE
Requires-Dist: requests
Requires-Dist: beautifulsoup4
Dynamic: license-file
